modelling/__init__.py
modelling/conversion.py
modelling/database.py
modelling/epanet.py
modelling/etabs.py
modelling/functions.py
modelling/gauges.py
modelling/geometryclean.py
modelling/plotting.py
modelling/wslnetwork.py
modelling2-0.1.dist-info/LICENSE.txt
modelling2-0.1.dist-info/METADATA
modelling2-0.1.dist-info/WHEEL
modelling2-0.1.dist-info/top_level.txt
modelling2-0.1.dist-info/RECORD
