Metadata-Version: 2.1
Name: modelling2
Version: 0.1
Summary: Tools used for hydraulic modelling
Home-page: UNKNOWN
Author: James Thorne
Author-email: james.thorne@mottmac.com
License: MIT
Platform: UNKNOWN
Requires-Dist: geopandas
Requires-Dist: pandas
Requires-Dist: datetime
Requires-Dist: numpy
Requires-Dist: gdal
Requires-Dist: arcgis
Requires-Dist: psycopg2
Requires-Dist: matplotlib
Requires-Dist: bokeh
Requires-Dist: geopy
Requires-Dist: networkx
